Py_FS/.DS_Store
Py_FS/__init__.py
Py_FS/evaluation.py
Py_FS/__pycache__/__init__.cpython-38.pyc
Py_FS/__pycache__/evaluation.cpython-38.pyc
Py_FS/datasets/.DS_Store
Py_FS/datasets/__init__.py
Py_FS/datasets/get_dataset.py
Py_FS/datasets/__pycache__/__init__.cpython-38.pyc
Py_FS/datasets/__pycache__/get_dataset.cpython-38.pyc
Py_FS/datasets/database/Arrhythmia.csv
Py_FS/datasets/database/BreastCancer.csv
Py_FS/datasets/database/BreastEW.csv
Py_FS/datasets/database/CongressEW.csv
Py_FS/datasets/database/Digits.csv
Py_FS/datasets/database/Exactly.csv
Py_FS/datasets/database/Exactly2.csv
Py_FS/datasets/database/Glass.csv
Py_FS/datasets/database/HeartEW.csv
Py_FS/datasets/database/Hill-valley.csv
Py_FS/datasets/database/Horse.csv
Py_FS/datasets/database/Ionosphere.csv
Py_FS/datasets/database/Iris.csv
Py_FS/datasets/database/KrVsKpEW.csv
Py_FS/datasets/database/Lymphography.csv
Py_FS/datasets/database/M-of-n.csv
Py_FS/datasets/database/Madelon.csv
Py_FS/datasets/database/Monk1.csv
Py_FS/datasets/database/Monk2.csv
Py_FS/datasets/database/Monk3.csv
Py_FS/datasets/database/PenglungEW.csv
Py_FS/datasets/database/Sonar.csv
Py_FS/datasets/database/Soybean-small.csv
Py_FS/datasets/database/SpectEW.csv
Py_FS/datasets/database/Tic-tac-toe.csv
Py_FS/datasets/database/Vote.csv
Py_FS/datasets/database/Vowel.csv
Py_FS/datasets/database/WaveformEW.csv
Py_FS/datasets/database/Wine.csv
Py_FS/datasets/database/Zoo.csv
Py_FS/datasets/database/__init__.py
Py_FS/datasets/database/Knapsack/README.md
Py_FS/datasets/database/Knapsack/knapsack_data_extractor.py
Py_FS/datasets/database/Knapsack/ks_12a.txt
Py_FS/datasets/database/Knapsack/ks_12b.txt
Py_FS/datasets/database/Knapsack/ks_12c.txt
Py_FS/datasets/database/Knapsack/ks_12d.txt
Py_FS/datasets/database/Knapsack/ks_12e.txt
Py_FS/datasets/database/Knapsack/ks_16a.txt
Py_FS/datasets/database/Knapsack/ks_16b.txt
Py_FS/datasets/database/Knapsack/ks_16c.txt
Py_FS/datasets/database/Knapsack/ks_16d.txt
Py_FS/datasets/database/Knapsack/ks_16e.txt
Py_FS-0.2.1.dist-info/LICENSE
Py_FS-0.2.1.dist-info/METADATA
Py_FS-0.2.1.dist-info/WHEEL
Py_FS-0.2.1.dist-info/top_level.txt
Py_FS-0.2.1.dist-info/RECORD
