Metadata-Version: 2.1
Name: Py_FS
Version: 0.2.1
Summary: A Python Package for Feature Selection
Home-page: https://github.com/CMATER-JUCS/Py-FS
Author: Ritam Guha
Author-email: ritamguha16@gmail.com
Classifier: Programming Language :: Python :: 3
Classifier: License :: OSI Approved :: MIT License
Classifier: Operating System :: OS Independent
License-File: LICENSE
